ppplca/__init__.py
ppplca/Actions/bw_base_set_up.py
ppplca/Actions/CreateAgriActivities.py
ppplca/Actions/CreateHeatActivities.py
ppplca/Actions/CreateParams.py
ppplca/Actions/FindActivityLocation.py
ppplca/Actions/import_agrifootprint_db_functions.py
ppplca/Actions/name_match.py
ppplca/Actions/Plot.py
ppplca/Commands/InstallCommand.py
ppplca/Commands/RunCommand.py
ppplca/Commands/SetupDatabaseCommand.py
ppplca/config.py
ppplca/data/activity_names/activity_names.csv
ppplca/data/activity_names/activity_names.xlsx
ppplca/data/grid_shares/Electricity_grid_shares_CN_pea.csv
ppplca/data/grid_shares/Electricity_grid_shares_CN_soy.csv
ppplca/data/grid_shares/Electricity_grid_shares_CN_wheat.csv
ppplca/data/grid_shares/Electricity_grid_shares_US_soy.csv
ppplca/data/grid_shares/Electricity_grid_shares_US_wheat.csv
ppplca/data/production_countries/production_countries_pea_Europe.csv
ppplca/data/production_countries/production_countries_soy_Europe.csv
ppplca/data/production_countries/production_countries_wheat_Europe.csv
ppplca/data/regionalization_setup/Agrifootprint_6_economic_new.json
ppplca/data/regionalization_setup/cf_aware_processed.csv
ppplca/data/regionalization_setup/cf_biodiversity_processed_new.csv
ppplca/data/regionalization_setup/cf_pm_image_regions.csv
ppplca/data/regionalization_setup/Country.xlsx
ppplca/data/regionalization_setup/Ecoinvent_310_to_IMAGE_conversion.csv
ppplca/data/regionalization_setup/ghg_cfs_ipcc_ar6.xlsx
ppplca/data/regionalization_setup/Locations_in_lca_db_new.csv
ppplca/data/regionalization_setup/Scherer_land_use_match.csv
ppplca/data/transport/Distances_european_countries_final.csv
ppplca/data/transport/Europe_distance_from_port.csv
ppplca/data/transport/European_countries.csv
ppplca/data/transport/Production_to_port_distance.csv
ppplca/data/transport/Transport_between_ports.csv
ppplca/data/transport/Transport_Data.xlsx
ppplca/Models/Activity.py
ppplca/Models/Country.py
ppplca/Models/Exchange.py
ppplca/Models/LCA.py
ppplca-0.2.34.dist-info/LICENSE
ppplca-0.2.34.dist-info/METADATA
ppplca-0.2.34.dist-info/WHEEL
ppplca-0.2.34.dist-info/RECORD
