Metadata-Version: 2.3
Name: ppplca
Version: 0.2.34
Summary: 
License: MIT
Author: Armin Siegrist
Author-email: armin.siegrist@hest.ethz.ch
Requires-Python: >=3.12
Classifier: License :: OSI Approved :: MIT License
Classifier: Programming Language :: Python :: 3
Classifier: Programming Language :: Python :: 3.12
Classifier: Programming Language :: Python :: 3.13
Requires-Dist: brightway2 (>=2.4)
Requires-Dist: ecoinvent_interface (==3.1)
Requires-Dist: matplotlib (>=3.9)
Requires-Dist: numpy (>=1.26)
Requires-Dist: pandas (>=2.2)
Requires-Dist: siegrist-lca-algebraic
Project-URL: Repository, https://github.com/siegarmi/ppplca
